{
  "extends": "../js/common.jsconfig.json",
  "compilerOptions": {
    "target": "ES2015",
    "module": "ES2015",
    "moduleResolution": "node",
    "allowJs": false,
    "sourceMap": true,
    "verbatimModuleSyntax": true,
    "esModuleInterop": true,
    "resolveJsonModule": true,
    "strict": true,
    "noUnusedLocals": true,
    "noUnusedParameters": true,
    "noImplicitReturns": true,
    "noFallthroughCasesInSwitch": true,
    "noImplicitOverride": true,
    "noUncheckedIndexedAccess": false,
    "skipLibCheck": true,
    "jsx": "react",
    "importHelpers": true,
    "incremental": true
  }
}
